Metadata-Version: 2.4
Name: whisper-s2t-reborn
Version: 1.4.4
Summary: A streamlined Speech-to-Text pipeline for Whisper using CTranslate2
Author: Blair Chintella
License: MIT
Project-URL: Homepage, https://github.com/BBC-Esq/WhisperS2T-reborn
Requires-Python: <3.14,>=3.11
Requires-Dist: ctranslate2==4.6.2
Requires-Dist: huggingface-hub
Requires-Dist: numpy<3.0.0,>=1.26.4
Requires-Dist: platformdirs
Requires-Dist: requests
Requires-Dist: tokenizers
Requires-Dist: torch<=2.9.1,>=2.8.0
Requires-Dist: tqdm
